MANIFEST.in
setup.py
mdemos/__init__.py
mdemos.metrics.egg-info/PKG-INFO
mdemos.metrics.egg-info/SOURCES.txt
mdemos.metrics.egg-info/dependency_links.txt
mdemos.metrics.egg-info/entry_points.txt
mdemos.metrics.egg-info/namespace_packages.txt
mdemos.metrics.egg-info/not-zip-safe
mdemos.metrics.egg-info/requires.txt
mdemos.metrics.egg-info/top_level.txt
mdemos/metrics/__init__.py
mdemos/metrics/consumers/__init__.py
mdemos/metrics/consumers/metrics_consumer.py
mdemos/metrics/producers/__init__.py
mdemos/metrics/producers/metrics_stream.py
mdemos/metrics/widgets/__init__.py
mdemos/metrics/widgets/metrics.py
mdemos/metrics/widgets/templates/__init__.py
mdemos/metrics/widgets/templates/__init__.pyc
mdemos/metrics/widgets/templates/metrics.mak