Metadata-Version: 1.0
Name: mdemos.metrics
Version: 1.0.0
Summary: Moksha Metrics App
Home-page: http://moksha.fedorahosted.org
Author: Luke Macken
Author-email: lmacken@redhat.com
License: ASL 2.0
Platform: UNKNOWN
